LICENSE
MANIFEST.in
README
setup.py
examples/reading/rtf15.py
examples/reading/xhtml.py
examples/writing/latex.py
examples/writing/pdf.py
examples/writing/plaintext.py
examples/writing/pythonDoc.py
examples/writing/rst.py
examples/writing/rtf15.py
examples/writing/xhtml.py
pyth/__init__.py
pyth/document.py
pyth/errors.py
pyth/format.py
pyth.egg-info/PKG-INFO
pyth.egg-info/SOURCES.txt
pyth.egg-info/dependency_links.txt
pyth.egg-info/not-zip-safe
pyth.egg-info/top_level.txt
pyth/encodings/__init__.py
pyth/encodings/symbol.py
pyth/plugins/__init__.py
pyth/plugins/latex/__init__.py
pyth/plugins/latex/writer.py
pyth/plugins/pdf/__init__.py
pyth/plugins/pdf/writer.py
pyth/plugins/plaintext/__init__.py
pyth/plugins/plaintext/writer.py
pyth/plugins/python/__init__.py
pyth/plugins/python/reader.py
pyth/plugins/rst/__init__.py
pyth/plugins/rst/writer.py
pyth/plugins/rtf15/__init__.py
pyth/plugins/rtf15/reader.py
pyth/plugins/rtf15/writer.py
pyth/plugins/xhtml/__init__.py
pyth/plugins/xhtml/css.py
pyth/plugins/xhtml/reader.py
pyth/plugins/xhtml/writer.py
tests/test_readxhtml.py
tests/test_writelatex.py
tests/test_writepdf.py